ambassador/__init__.py
ambassador/__main__.py
ambassador/eicar.py
ambassador/filesystem.py
arbiter/__init__.py
arbiter/__main__.py
arbiter/clamav.py
arbiter/eicar.py
arbiter/producer.py
arbiter/verbatim.py
arbiter/verbatimdb/__init__.py
arbiter/verbatimdb/__main__.py
arbiter/verbatimdb/db.py
balancemanager/__init__.py
balancemanager/__main__.py
liveness/__init__.py
liveness/__main__.py
microengine/__init__.py
microengine/__main__.py
microengine/clamav.py
microengine/eicar.py
microengine/multi.py
microengine/producer.py
microengine/scratch.py
microengine/yara.py
microengine/bidstrategy/__init__.py
microengine/bidstrategy/aggressive.py
microengine/bidstrategy/conservative.py
microengine/bidstrategy/default.py
polyswarmclient/__init__.py
polyswarmclient/abstractambassador.py
polyswarmclient/abstractarbiter.py
polyswarmclient/abstractmicroengine.py
polyswarmclient/abstractscanner.py
polyswarmclient/backoff_wrapper.py
polyswarmclient/bidstrategy.py
polyswarmclient/config.py
polyswarmclient/corpus.py
polyswarmclient/events.py
polyswarmclient/exceptions.py
polyswarmclient/log_formatter.py
polyswarmclient/parameters.py
polyswarmclient/request_rate_limit.py
polyswarmclient/utils.py
polyswarmclient/ethereum/__init__.py
polyswarmclient/ethereum/balanceclient.py
polyswarmclient/ethereum/bloom.py
polyswarmclient/ethereum/offersclient.py
polyswarmclient/ethereum/relayclient.py
polyswarmclient/ethereum/stakingclient.py
polyswarmclient/ethereum/verifiers.py
polyswarmclient/ethereum/bountiesclient/__init__.py
polyswarmclient/ethereum/bountiesclient/base.py
polyswarmclient/ethereum/bountiesclient/transaction.py
polyswarmclient/ethereum/transaction/__init__.py
polyswarmclient/ethereum/transaction/base.py
polyswarmclient/ethereum/transaction/noncemanager.py
polyswarmclient/fast/__init__.py
polyswarmclient/fast/balanceclient.py
polyswarmclient/fast/bountiesclient.py
polyswarmclient/fast/offersclient.py
polyswarmclient/fast/relayclient.py
polyswarmclient/fast/stakingclient.py
polyswarm_client-2.13.3.dist-info/LICENSE
polyswarm_client-2.13.3.dist-info/METADATA
polyswarm_client-2.13.3.dist-info/WHEEL
polyswarm_client-2.13.3.dist-info/entry_points.txt
polyswarm_client-2.13.3.dist-info/top_level.txt
polyswarm_client-2.13.3.dist-info/RECORD
