Metadata-Version: 2.1
Name: polyswarm-client
Version: 2.13.3
Summary: Client library to simplify interacting with a polyswarmd instance
Home-page: https://github.com/polyswarm/polyswarm-client
Author: PolySwarm Developers
Author-email: info@polyswarm.io
License: MIT
Platform: UNKNOWN
Classifier: Intended Audience :: Developers
Classifier: License :: OSI Approved :: MIT License
Classifier: Operating System :: OS Independent
Classifier: Programming Language :: Python :: 3.6
Classifier: Programming Language :: Python :: 3.7
Classifier: Programming Language :: Python :: 3.8
Requires-Python: >=3.6.5,<4
License-File: LICENSE
Requires-Dist: aiohttp (==3.7.4)
Requires-Dist: aiodns (~=2.0.0)
Requires-Dist: aioredis (~=1.3.1)
Requires-Dist: aioresponses (==0.7.2)
Requires-Dist: aiorwlock (~=0.6.0)
Requires-Dist: cachetools (~=4.1.0)
Requires-Dist: asynctest (==0.13.0)
Requires-Dist: backoff (~=1.10.0)
Requires-Dist: base58 (~=2.0.0)
Requires-Dist: click (~=7.1.2)
Requires-Dist: hexbytes (~=0.2.0)
Requires-Dist: polyswarm-artifact (~=1.4.1)
Requires-Dist: polyswarm-transaction (<1.0.0,>=0.2.0)
Requires-Dist: pycryptodome (~=3.10.1)
Requires-Dist: python-json-logger (~=0.1.9)
Requires-Dist: web3 (~=5.6.0)
Requires-Dist: websockets (~=8.1)
Requires-Dist: yara-python (~=4.0.1)
Requires-Dist: python-magic (~=0.4.15) ; platform_system == "Linux"
Requires-Dist: python-magic-bin (~=0.4.14) ; platform_system == "Windows"
